{"sheet1":[{
    "postal_add": "104, 1F, Shri Ganesh Appartment, Ews, Sector-31, Gurugram", 
    "zone": "4", 
    "gender": "", 
    "area_name": "SECTOR 31", 
    "relation_type": "S/O", 
    "relation_name": "Sukhram", 
    "mobile_no": "8800005060", 
    "new_postal_add": "", 
    "owenr_name": "Gajraj Singh", 
    "unique_property_id": "214C2326UX2FP4"
},
{
    "postal_add": "97A, Sector-32, Gurugram", 
    "zone": "4", 
    "gender": "", 
    "area_name": "SECTOR 32", 
    "relation_type": "", 
    "relation_name": "", 
    "mobile_no": "9810192959", 
    "new_postal_add": "", 
    "owenr_name": "M/s Babbar Films Pvt. Ltd.", 
    "unique_property_id": "225C58U25A"
},
{
    "postal_add": "A-101, Ambe Residency Khewat No. 165, Min/ 215, 166/220, Sector-39, Gurugram", 
    "zone": "4", 
    "gender": "", 
    "area_name": "SECTOR 39", 
    "relation_type": "", 
    "relation_name": "", 
    "mobile_no": "9810067157", 
    "new_postal_add": "", 
    "owenr_name": "Sh. Sanjay", 
    "unique_property_id": "225C881U101H1"
},
{
    "postal_add": "B-104,1F, Ambe Residency Khewat No. 165 Min/215, 166/220, Sector 39, Gurugram", 
    "zone": "4", 
    "gender": "", 
    "area_name": "SECTOR 39", 
    "relation_type": "", 
    "relation_name": "", 
    "mobile_no": "9810067157", 
    "new_postal_add": "", 
    "owenr_name": "Prahlad", 
    "unique_property_id": "225C881U101H10"
},
{
    "postal_add": "B-105,1F, Ambe Residency, Khewat No. 165 Min/215, 166/220, Sector 39, Gurugram", 
    "zone": "4", 
    "gender": "", 
    "area_name": "SECTOR 39", 
    "relation_type": "", 
    "relation_name": "", 
    "mobile_no": "9810067157", 
    "new_postal_add": "", 
    "owenr_name": "Prahlad", 
    "unique_property_id": "225C881U101H11"
},
{
    "postal_add": "B-106, 1F, Ambe Residency, Khewat No. 165 Min/215, 166/220, Sector 39, Gurugram", 
    "zone": "4", 
    "gender": "", 
    "area_name": "SECTOR 39", 
    "relation_type": "", 
    "relation_name": "", 
    "mobile_no": "9810067157", 
    "new_postal_add": "", 
    "owenr_name": "Prahlad", 
    "unique_property_id": "225C881U101H12"
},
{
    "postal_add": "A-201, 2F, Ambe Residency, Khewat No. 165 Min/215, 166/220, Sector 39, Gurugram", 
    "zone": "4", 
    "gender": "", 
    "area_name": "SECTOR 39", 
    "relation_type": "", 
    "relation_name": "", 
    "mobile_no": "9810067157", 
    "new_postal_add": "", 
    "owenr_name": "Dhankar", 
    "unique_property_id": "225C881U101H13"
},
{
    "postal_add": "B-202, 2F, Ambe Residency, Khewat No 165 Min/215 166/220, Sector 39, Gurugram", 
    "zone": "4", 
    "gender": "", 
    "area_name": "SECTOR 39", 
    "relation_type": "", 
    "relation_name": "", 
    "mobile_no": "9810067157", 
    "new_postal_add": "", 
    "owenr_name": "Karanjeet", 
    "unique_property_id": "225C881U101H14"
},
{
    "postal_add": "A-203, 2F, Ambe Residency, Khewat No 165 Min/215, 166/220, Sector 39, Gurugram", 
    "zone": "4", 
    "gender": "", 
    "area_name": "SECTOR 39", 
    "relation_type": "", 
    "relation_name": "", 
    "mobile_no": "9810067157", 
    "new_postal_add": "", 
    "owenr_name": "Ravi ", 
    "unique_property_id": "225C881U101H15"
},
{
    "postal_add": "A-204, 2F, Ambe Residency, Khewat No. 165 Min/215, 166/220, Sector 39, Gurugram", 
    "zone": "4", 
    "gender": "", 
    "area_name": "SECTOR 39", 
    "relation_type": "", 
    "relation_name": "", 
    "mobile_no": "9810067157", 
    "new_postal_add": "", 
    "owenr_name": "Dilbag Punia", 
    "unique_property_id": "225C881U101H16"
},
{
    "postal_add": "A-205,2F, Ambe Residency, Khewat No 165 Min/215, 166/220, Sector 39, Gurugram", 
    "zone": "4", 
    "gender": "", 
    "area_name": "SECTOR 39", 
    "relation_type": "", 
    "relation_name": "", 
    "mobile_no": "9810067157", 
    "new_postal_add": "", 
    "owenr_name": "Wazir Punia", 
    "unique_property_id": "225C881U101H17"
},
{
    "postal_add": "A-206, 2F, Ambe Residency, Khewat No 165 Min/215, 166/220, Sector 39, Gurugram", 
    "zone": "4", 
    "gender": "", 
    "area_name": "SECTOR 39", 
    "relation_type": "", 
    "relation_name": "", 
    "mobile_no": "9810067157", 
    "new_postal_add": "", 
    "owenr_name": "Bakul", 
    "unique_property_id": "225C881U101H18"
},
{
    "postal_add": "B-201, 2F, Ambe Residency, Khewat No 165 Min/215, 166/220, Sector 39, Gurugram", 
    "zone": "4", 
    "gender": "", 
    "area_name": "SECTOR 39", 
    "relation_type": "", 
    "relation_name": "", 
    "mobile_no": "9810067157", 
    "new_postal_add": "", 
    "owenr_name": "Krishanjeet", 
    "unique_property_id": "225C881U101H19"
},
{
    "postal_add": "A-102,1F, Ambe Residency, Khewat No.  165 Min/215, 166/220, Sector 39, Gurugram", 
    "zone": "4", 
    "gender": "", 
    "area_name": "SECTOR 39", 
    "relation_type": "", 
    "relation_name": "", 
    "mobile_no": "9810067157", 
    "new_postal_add": "", 
    "owenr_name": "Jaibhagwan", 
    "unique_property_id": "225C881U101H2"
},
{
    "postal_add": "B-202, 2F, Ambe Residency, Khewat No. 165 Min/215, 166/220, Sector 39, Gurugram", 
    "zone": "4", 
    "gender": "", 
    "area_name": "SECTOR 39", 
    "relation_type": "", 
    "relation_name": "", 
    "mobile_no": "9810067157", 
    "new_postal_add": "", 
    "owenr_name": "Om Parkash", 
    "unique_property_id": "225C881U101H20"
},
{
    "postal_add": "B-203, 2F, Ambe Residency, Khewat No 165 Min/215, 166/220, Sector 39, Gurugram", 
    "zone": "4", 
    "gender": "", 
    "area_name": "SECTOR 39", 
    "relation_type": "", 
    "relation_name": "", 
    "mobile_no": "9810067157", 
    "new_postal_add": "", 
    "owenr_name": "Satbir Thakran", 
    "unique_property_id": "225C881U101H21"
},
{
    "postal_add": "B-204, 2F, Ambe Residency, Khewat No. 165 Min/215, 166/220, Sector 39, Gurugram", 
    "zone": "4", 
    "gender": "", 
    "area_name": "SECTOR 39", 
    "relation_type": "", 
    "relation_name": "", 
    "mobile_no": "9810067157", 
    "new_postal_add": "", 
    "owenr_name": "Kuldeep", 
    "unique_property_id": "225C881U101H22"
},
{
    "postal_add": "B-205, 2F, Ambe Residency, Khewat No 165 Min/215, 166/220, Sector 39, Gurugram", 
    "zone": "4", 
    "gender": "", 
    "area_name": "SECTOR 39", 
    "relation_type": "", 
    "relation_name": "", 
    "mobile_no": "9810067157", 
    "new_postal_add": "", 
    "owenr_name": "Punam Sangwan", 
    "unique_property_id": "225C881U101H23"
},
{
    "postal_add": "B-206,2F, Ambe Residency, Khewat No. 165 Min/215, 166/220, Sector 39, Gurugram", 
    "zone": "4", 
    "gender": "", 
    "area_name": "SECTOR 39", 
    "relation_type": "", 
    "relation_name": "", 
    "mobile_no": "9810067157", 
    "new_postal_add": "", 
    "owenr_name": "Rajender Beniwal", 
    "unique_property_id": "225C881U101H24"
},
{
    "postal_add": "A-301, 3F, Ambe Residency, Khewat No. 165 Min/215, 166/220, Sector 39,Gurugram", 
    "zone": "4", 
    "gender": "", 
    "area_name": "SECTOR 39", 
    "relation_type": "", 
    "relation_name": "", 
    "mobile_no": "9810067157", 
    "new_postal_add": "", 
    "owenr_name": "Vinod Sharma", 
    "unique_property_id": "225C881U101H25"
},
{
    "postal_add": "A-302, 3F, Ambe Residency, Khewat No 165 Min/215, 166/220, Sector 39, Gurugram", 
    "zone": "4", 
    "gender": "", 
    "area_name": "SECTOR 39", 
    "relation_type": "", 
    "relation_name": "", 
    "mobile_no": "9810067157", 
    "new_postal_add": "", 
    "owenr_name": "Neha", 
    "unique_property_id": "225C881U101H26"
},
{
    "postal_add": "A-303, 3F, Ambe Residency, Khewat No. 165 Min/215, 166/220, Sector 39, Gurugram", 
    "zone": "4", 
    "gender": "", 
    "area_name": "SECTOR 39", 
    "relation_type": "", 
    "relation_name": "", 
    "mobile_no": "9810067157", 
    "new_postal_add": "", 
    "owenr_name": "Pramod Agrawal", 
    "unique_property_id": "225C881U101H27"
},
{
    "postal_add": "A-304, 3F, Ambe Residency, Khewat No. 165 Min/215, 166/220, Sector 39, Gurugram ", 
    "zone": "4", 
    "gender": "", 
    "area_name": "SECTOR 39", 
    "relation_type": "", 
    "relation_name": "", 
    "mobile_no": "9810067157", 
    "new_postal_add": "", 
    "owenr_name": "Rambhagat Punia", 
    "unique_property_id": "225C881U101H28"
},
{
    "postal_add": "A-305, 3F, Ambe Residency, Khewat No. 165/215, 166/220, Sector 39, Gurugram", 
    "zone": "4", 
    "gender": "", 
    "area_name": "SECTOR 39", 
    "relation_type": "", 
    "relation_name": "", 
    "mobile_no": "9810067157", 
    "new_postal_add": "", 
    "owenr_name": "Surender Bhardwaj", 
    "unique_property_id": "225C881U101H29"
},
{
    "postal_add": "A-103,1F,Ambe residency, Khewat No. 165 Min/215, 166/220, Sector 39, Gurugram", 
    "zone": "4", 
    "gender": "", 
    "area_name": "SECTOR 39", 
    "relation_type": "", 
    "relation_name": "", 
    "mobile_no": "9810067157", 
    "new_postal_add": "", 
    "owenr_name": "Sanjay", 
    "unique_property_id": "225C881U101H3"
},
{
    "postal_add": "A-306, 3F, Ambe Residency, Khewat No. 165 Min/215, 166/220, Sector 39, Gurugram", 
    "zone": "4", 
    "gender": "", 
    "area_name": "SECTOR 39", 
    "relation_type": "", 
    "relation_name": "", 
    "mobile_no": "9810067157", 
    "new_postal_add": "", 
    "owenr_name": "Mahabir Thakran", 
    "unique_property_id": "225C881U101H30"
},
{
    "postal_add": "B-301, 3F, Ambe Residency, Khewat No. 165 Min/215, 166/220, Sector 39, Gurugram", 
    "zone": "4", 
    "gender": "", 
    "area_name": "SECTOR 39", 
    "relation_type": "", 
    "relation_name": "", 
    "mobile_no": "9810067157", 
    "new_postal_add": "", 
    "owenr_name": "Kiran kakkar", 
    "unique_property_id": "225C881U101H31"
},
{
    "postal_add": "B-302, 3F, Ambe Residency, Khewat No 165 Min/215, 166/220, Sector 39, Gurugram", 
    "zone": "4", 
    "gender": "", 
    "area_name": "SECTOR 39", 
    "relation_type": "", 
    "relation_name": "", 
    "mobile_no": "9810067157", 
    "new_postal_add": "", 
    "owenr_name": "Prachi Gaur", 
    "unique_property_id": "225C881U101H32"
},
{
    "postal_add": "B-303, 3F, Ambe Residency, Khewat No. 165 Min/215, 166/220, Sector 39, Gurugram", 
    "zone": "4", 
    "gender": "", 
    "area_name": "SECTOR 39", 
    "relation_type": "", 
    "relation_name": "", 
    "mobile_no": "9810067157", 
    "new_postal_add": "", 
    "owenr_name": "Meenu Sharma", 
    "unique_property_id": "225C881U101H33"
},
{
    "postal_add": "B-304, 3F,Ambe Residency, Khewat No. 165 Min/215, 166/220, Sector 39,Gurugram", 
    "zone": "4", 
    "gender": "", 
    "area_name": "SECTOR 39", 
    "relation_type": "", 
    "relation_name": "", 
    "mobile_no": "9810067157", 
    "new_postal_add": "", 
    "owenr_name": "Meenu Sharma", 
    "unique_property_id": "225C881U101H34"
},
{
    "postal_add": "B-305, 3F, Ambe Residency, Khewat No. 165 Min/215, 166/220, Sector 39, Gurugram", 
    "zone": "4", 
    "gender": "", 
    "area_name": "SECTOR 39", 
    "relation_type": "", 
    "relation_name": "", 
    "mobile_no": "9810067157", 
    "new_postal_add": "", 
    "owenr_name": "Indumati Sharma", 
    "unique_property_id": "225C881U101H35"
},
{
    "postal_add": "B-306, 3F, Ambey Residency, Khewat No. 165 Min/215, 166/220, Sector 39, Gurugram", 
    "zone": "4", 
    "gender": "", 
    "area_name": "SECTOR 39", 
    "relation_type": "", 
    "relation_name": "", 
    "mobile_no": "9810067157", 
    "new_postal_add": "", 
    "owenr_name": "Vacant", 
    "unique_property_id": "225C881U101H36"
},
{
    "postal_add": "A-401, 4F, Ambe Residency, Khewat No. 165 Min/215, 166/220, Sector 39, Gurugram", 
    "zone": "4", 
    "gender": "", 
    "area_name": "SECTOR 39", 
    "relation_type": "", 
    "relation_name": "", 
    "mobile_no": "9810067157", 
    "new_postal_add": "", 
    "owenr_name": "Surender", 
    "unique_property_id": "225C881U101H37"
},
{
    "postal_add": "A-402, 4F, Ambe Residency, Khewat No. 165 Min/215, 166/220, Sector 39, Gurugram", 
    "zone": "4", 
    "gender": "", 
    "area_name": "SECTOR 39", 
    "relation_type": "", 
    "relation_name": "", 
    "mobile_no": "9810067157", 
    "new_postal_add": "", 
    "owenr_name": "Karanjeet", 
    "unique_property_id": "225C881U101H38"
},
{
    "postal_add": "A-403, 4F, Ambe Residency, Khewat No 165 Min/215, 166/220, Sector 39, Gurugram", 
    "zone": "4", 
    "gender": "", 
    "area_name": "SECTOR 39", 
    "relation_type": "", 
    "relation_name": "", 
    "mobile_no": "9810067157", 
    "new_postal_add": "", 
    "owenr_name": "Vacant", 
    "unique_property_id": "225C881U101H39"
},
{
    "postal_add": "A-104,1F, Ambe Residency, Khewat No. 165 MIn /215, 166/220, Sector 39, Gurugram", 
    "zone": "4", 
    "gender": "", 
    "area_name": "SECTOR 39", 
    "relation_type": "", 
    "relation_name": "", 
    "mobile_no": "9810067157", 
    "new_postal_add": "", 
    "owenr_name": "Bhup Singh", 
    "unique_property_id": "225C881U101H4"
},
{
    "postal_add": "A-404, 4F, Ambe Residency, Khewat No. 165 Min/215, 166/220, Sector 39, Gurugram", 
    "zone": "4", 
    "gender": "", 
    "area_name": "SECTOR 39", 
    "relation_type": "", 
    "relation_name": "", 
    "mobile_no": "9810067157", 
    "new_postal_add": "", 
    "owenr_name": "Vacant", 
    "unique_property_id": "225C881U101H40"
},
{
    "postal_add": "A-405, 4F, Ambe Residency, Khewat No. 165 Min/215, 166/220, Sector 39, Gurugram", 
    "zone": "4", 
    "gender": "", 
    "area_name": "SECTOR 39", 
    "relation_type": "", 
    "relation_name": "", 
    "mobile_no": "9810067157", 
    "new_postal_add": "", 
    "owenr_name": "Harmit Kaur", 
    "unique_property_id": "225C881U101H41"
},
{
    "postal_add": "A-406, 4F, Ambe Residency, Khewat No. 165 Min/215, 166/220, Sector 39, Gurugram", 
    "zone": "4", 
    "gender": "", 
    "area_name": "SECTOR 39", 
    "relation_type": "", 
    "relation_name": "", 
    "mobile_no": "9810067157", 
    "new_postal_add": "", 
    "owenr_name": "Vacant", 
    "unique_property_id": "225C881U101H42"
},
{
    "postal_add": "B-401, 4F, Ambe Residency, Khewat No.165 Min/215, 166/220, Sector 39, Gurugram", 
    "zone": "4", 
    "gender": "", 
    "area_name": "SECTOR 39", 
    "relation_type": "", 
    "relation_name": "", 
    "mobile_no": "9810067157", 
    "new_postal_add": "", 
    "owenr_name": "Tarun Sharma", 
    "unique_property_id": "225C881U101H43"
},
{
    "postal_add": "B-402, 4F, Ambe Residency, Khewat No 165 Min/125, 166/220, Sector 39, Gurugram", 
    "zone": "4", 
    "gender": "", 
    "area_name": "SECTOR 39", 
    "relation_type": "", 
    "relation_name": "", 
    "mobile_no": "9810067157", 
    "new_postal_add": "", 
    "owenr_name": "Vacant", 
    "unique_property_id": "225C881U101H44"
},
{
    "postal_add": "B-403, 4F, Ambe Residency, Khewat No. 165 Min/215, 166/220, Sector 39, Gurugram", 
    "zone": "4", 
    "gender": "", 
    "area_name": "SECTOR 39", 
    "relation_type": "", 
    "relation_name": "", 
    "mobile_no": "9810067157", 
    "new_postal_add": "", 
    "owenr_name": "Subhash Chnader", 
    "unique_property_id": "225C881U101H45"
},
{
    "postal_add": "B-404, 4F, Ambe Residency, Khewat No 165 Min/215, 166/220, Sector 39, Gurugram", 
    "zone": "4", 
    "gender": "", 
    "area_name": "SECTOR 39", 
    "relation_type": "", 
    "relation_name": "", 
    "mobile_no": "9810067157", 
    "new_postal_add": "", 
    "owenr_name": "Vacant", 
    "unique_property_id": "225C881U101H46"
},
{
    "postal_add": "B-405, 4F, Ambe Residency, Khewat No. 165 Min/215, 166/220, Sector 39, Gurugram ", 
    "zone": "4", 
    "gender": "", 
    "area_name": "SECTOR 39", 
    "relation_type": "", 
    "relation_name": "", 
    "mobile_no": "9810067157", 
    "new_postal_add": "", 
    "owenr_name": "Sunil Wadhwa", 
    "unique_property_id": "225C881U101H47"
},
{
    "postal_add": "A-105,1F, Ambe Residency, Khewat No 165 Min/215, 166/220, Sector 39, Gurugram", 
    "zone": "4", 
    "gender": "", 
    "area_name": "SECTOR 39", 
    "relation_type": "", 
    "relation_name": "", 
    "mobile_no": "9810067157", 
    "new_postal_add": "", 
    "owenr_name": "Sanjay", 
    "unique_property_id": "225C881U101H5"
},
{
    "postal_add": "A-106, 1F, Ambe Residency, Khewat No 165 Min/215, 166/220, Sector 39, Gurugram", 
    "zone": "4", 
    "gender": "", 
    "area_name": "SECTOR 39", 
    "relation_type": "", 
    "relation_name": "", 
    "mobile_no": "9810067157", 
    "new_postal_add": "", 
    "owenr_name": "Balbir", 
    "unique_property_id": "225C881U101H6"
},
{
    "postal_add": "B-101, 1F, Ambe Residency, Khewat No. 165 Min/215, 166/220, Sector 39, Gurugram", 
    "zone": "4", 
    "gender": "", 
    "area_name": "SECTOR 39", 
    "relation_type": "", 
    "relation_name": "", 
    "mobile_no": "9810067157", 
    "new_postal_add": "", 
    "owenr_name": "Surjeet", 
    "unique_property_id": "225C881U101H7"
},
{
    "postal_add": "B-102, 1F, Ambe Residency, Khewat No. 165 MIn/215, 166/220, Sector 39, Gurugram  ", 
    "zone": "4", 
    "gender": "", 
    "area_name": "SECTOR 39", 
    "relation_type": "", 
    "relation_name": "", 
    "mobile_no": "9810067157", 
    "new_postal_add": "", 
    "owenr_name": "Rajesh", 
    "unique_property_id": "225C881U101H8"
},
{
    "postal_add": "B-103,1F, Ambe Residency, Khewat No. 165 Min/215, 166/220, Sector 39, Gurugram", 
    "zone": "4", 
    "gender": "", 
    "area_name": "SECTOR 39", 
    "relation_type": "", 
    "relation_name": "", 
    "mobile_no": "9810067157", 
    "new_postal_add": "", 
    "owenr_name": "Prahlad", 
    "unique_property_id": "225C881U101H9"
},
{
    "postal_add": "Near 93, Saini Pura, Jharsa Village, Gurugram", 
    "zone": "4", 
    "gender": "", 
    "area_name": "Jharsa", 
    "relation_type": "S/O", 
    "relation_name": "Chander Singh", 
    "mobile_no": "9354045813", 
    "new_postal_add": "", 
    "owenr_name": "Hari Singh", 
    "unique_property_id": "226C1321U55P1"
},
{
    "postal_add": "Near 93, Saini Pura, Jharsa Village, Gurugram", 
    "zone": "4", 
    "gender": "", 
    "area_name": "Jharsa", 
    "relation_type": "S/O", 
    "relation_name": "Hari Singh", 
    "mobile_no": "9354045813", 
    "new_postal_add": "", 
    "owenr_name": "Rajesh", 
    "unique_property_id": "226C1321U55P2"
},
{
    "postal_add": "Near 93, Saini Pura, Jharsa Village, Gurugram", 
    "zone": "4", 
    "gender": "", 
    "area_name": "Jharsa", 
    "relation_type": "S/O", 
    "relation_name": "Sh. Hari Singh", 
    "mobile_no": "9354045813", 
    "new_postal_add": "", 
    "owenr_name": "Sanjay", 
    "unique_property_id": "226C1321U55P3"
},
{
    "postal_add": "Near 93, Saini Pura, Jharsa Village, Gurugram", 
    "zone": "4", 
    "gender": "", 
    "area_name": "Jharsa", 
    "relation_type": "S/O", 
    "relation_name": "Sh. Hari Singh", 
    "mobile_no": "9354045813", 
    "new_postal_add": "", 
    "owenr_name": "Mahender", 
    "unique_property_id": "226C1321U55P4"
},
{
    "postal_add": "187/1, Near Anganwari, Village- Jharsa, Gurugram", 
    "zone": "4", 
    "gender": "", 
    "area_name": "Jharsa", 
    "relation_type": "S/O", 
    "relation_name": "Sh. Mange Ram", 
    "mobile_no": "9899458247", 
    "new_postal_add": "", 
    "owenr_name": "Mr. Jal Singh", 
    "unique_property_id": "226C1595U117A187"
},
{
    "postal_add": "Jharsa Village, Gurugram", 
    "zone": "4", 
    "gender": "", 
    "area_name": "Jharsa", 
    "relation_type": "W/O", 
    "relation_name": "Jashmer Singh", 
    "mobile_no": "9911459703", 
    "new_postal_add": "", 
    "owenr_name": "Smt. Suman Lata", 
    "unique_property_id": "226C168U195P1"
},
{
    "postal_add": "Jharsa Village, Gurugram", 
    "zone": "4", 
    "gender": "", 
    "area_name": "Jharsa", 
    "relation_type": "W/O", 
    "relation_name": "Sh. Ramesh Kumar Thakran", 
    "mobile_no": "9643707160", 
    "new_postal_add": "", 
    "owenr_name": "Smt. Mukesh Devi", 
    "unique_property_id": "226C168U195P2"
},
{
    "postal_add": "Jharsa Village, Gurugram", 
    "zone": "4", 
    "gender": "", 
    "area_name": "Jharsa Village", 
    "relation_type": "S/O", 
    "relation_name": "Sh. Ramparsad", 
    "mobile_no": "9911308060", 
    "new_postal_add": "", 
    "owenr_name": "Sh. Jashmer Singh", 
    "unique_property_id": "227C2811U236P1"
},
{
    "postal_add": "H.No. 1439, 1F, Sector-46, Gurugram", 
    "zone": "4", 
    "gender": "", 
    "area_name": "SECTOR 46", 
    "relation_type": "W/O", 
    "relation_name": "Narinder Kumar Rajani", 
    "mobile_no": "7838185500", 
    "new_postal_add": "", 
    "owenr_name": "Mrs. Deepti Rajani", 
    "unique_property_id": "233C1107U35A"
},
{
    "postal_add": "1646, G.F, 1F, Sector-46, Gurugram", 
    "zone": "4", 
    "gender": "", 
    "area_name": "SECTOR 46", 
    "relation_type": "", 
    "relation_name": "", 
    "mobile_no": "9999999999", 
    "new_postal_add": "", 
    "owenr_name": "Smt. Harvinder Kaur", 
    "unique_property_id": "233C1326U76A"
},
{
    "postal_add": "H.No. 1658, G. F, Sector-46, Gurugram", 
    "zone": "4", 
    "gender": "", 
    "area_name": "SECTOR 46", 
    "relation_type": "", 
    "relation_name": "", 
    "mobile_no": "9958889495", 
    "new_postal_add": "", 
    "owenr_name": "Mrs. Parul Goel & Mr. Abhishek Bansal", 
    "unique_property_id": "233C1339U87P2"
},
{
    "postal_add": "1718, 1F, Sector-46, Gurugram", 
    "zone": "4", 
    "gender": "", 
    "area_name": "SECTOR 46", 
    "relation_type": "", 
    "relation_name": "", 
    "mobile_no": "9810001513", 
    "new_postal_add": "", 
    "owenr_name": "Mr. Ajay Mahajan & Mrs. Anshu Mahajan", 
    "unique_property_id": "233C1400U17P5A"
},
{
    "postal_add": "1718, 2F, Sector-46, Gurugram", 
    "zone": "4", 
    "gender": "", 
    "area_name": "SECTOR 46", 
    "relation_type": "", 
    "relation_name": "", 
    "mobile_no": "9810001513", 
    "new_postal_add": "", 
    "owenr_name": "Ms. Anupama Goyal & Mrs. Sujata Goel", 
    "unique_property_id": "233C1400U17P5B"
},
{
    "postal_add": "1816, 1F, 2F, Near Discovery Public School, Sector- 46, Gurugram", 
    "zone": "4", 
    "gender": "", 
    "area_name": "SECTOR 46", 
    "relation_type": "", 
    "relation_name": "", 
    "mobile_no": "9999999999", 
    "new_postal_add": "", 
    "owenr_name": "Unknown", 
    "unique_property_id": "233C1506U85XA"
},
{
    "postal_add": "1855,3F,Sector-46,Gurugram.", 
    "zone": "4", 
    "gender": "", 
    "area_name": "SECTOR 46", 
    "relation_type": "S/O", 
    "relation_name": "Sh. RR Chopra", 
    "mobile_no": "9868560995", 
    "new_postal_add": "", 
    "owenr_name": "Mr. Sunil Chopra", 
    "unique_property_id": "233C1546U13P68P3"
},
{
    "postal_add": "H.No. 2436, G.F, Sector-46, Gurugram", 
    "zone": "4", 
    "gender": "", 
    "area_name": "SECTOR 46", 
    "relation_type": "", 
    "relation_name": "", 
    "mobile_no": "7411782911", 
    "new_postal_add": "", 
    "owenr_name": "Mr. Sumit Gupta & Mrs. Monika Gupta", 
    "unique_property_id": "233C2182UM24P62B"
},
{
    "postal_add": "H.No. 2800, G.F, Sector-46, Gurugram", 
    "zone": "4", 
    "gender": "", 
    "area_name": "SECTOR 46", 
    "relation_type": "", 
    "relation_name": "", 
    "mobile_no": "9871881185", 
    "new_postal_add": "", 
    "owenr_name": "Mr. Ashish Walia & Mrs. Deepu Walia", 
    "unique_property_id": "233C2537UM28P1A"
},
{
    "postal_add": "2906, 1F, Sector-46, Gurugram", 
    "zone": "4", 
    "gender": "", 
    "area_name": "SECTOR 46", 
    "relation_type": "", 
    "relation_name": "", 
    "mobile_no": "9711433773", 
    "new_postal_add": "", 
    "owenr_name": "Mr. Vikram & Mr. Krishan Kumar", 
    "unique_property_id": "233C2641UA29P51A"
},
{
    "postal_add": "2906, 2F, Sector-46, Gurugram", 
    "zone": "4", 
    "gender": "", 
    "area_name": "SECTOR 46", 
    "relation_type": "", 
    "relation_name": "", 
    "mobile_no": "8826598199", 
    "new_postal_add": "", 
    "owenr_name": "Mr. Anuj Nagpal & Mrs. Neha Nagpal", 
    "unique_property_id": "233C2641UA29P51B"
},
{
    "postal_add": "860, 2F, Near Govt. Senior Secondary School, Sector-46, Gurugram", 
    "zone": "4", 
    "gender": "", 
    "area_name": "SECTOR 46", 
    "relation_type": "S/O", 
    "relation_name": "Sh. M.R. Singla", 
    "mobile_no": "9911365313", 
    "new_postal_add": "", 
    "owenr_name": "Mr. Manoj Kumar Singla", 
    "unique_property_id": "233C488U303A"
},
{
    "postal_add": "864, 1F, Sector-46, Gurugram", 
    "zone": "4", 
    "gender": "", 
    "area_name": "SECTOR 46", 
    "relation_type": "W/O", 
    "relation_name": "Mr. Satish Batra", 
    "mobile_no": "9873888148", 
    "new_postal_add": "", 
    "owenr_name": "Mrs. Sarita Batra", 
    "unique_property_id": "233C492U299A"
},
{
    "postal_add": "H.No. 1210, 2F, Sector-46, Gurugram", 
    "zone": "4", 
    "gender": "", 
    "area_name": "SECTOR 46", 
    "relation_type": "", 
    "relation_name": "", 
    "mobile_no": "9910710951", 
    "new_postal_add": "", 
    "owenr_name": "Mrs. Richa Verma & Mr. Sandeep Kaushik", 
    "unique_property_id": "233C846U438P2"
},
{
    "postal_add": "1212, 1F, 2F, Sector-46, Gurugram", 
    "zone": "4", 
    "gender": "", 
    "area_name": "SECTOR 46", 
    "relation_type": "", 
    "relation_name": "", 
    "mobile_no": "9540386960", 
    "new_postal_add": "", 
    "owenr_name": "Unknown", 
    "unique_property_id": "233C869U436A"
},
{
    "postal_add": "A-153/45, 1F, Block-A, Greenwood City, Gurugram", 
    "zone": "4", 
    "gender": "", 
    "area_name": "Greenwood City", 
    "relation_type": "", 
    "relation_name": "", 
    "mobile_no": "8800797505", 
    "new_postal_add": "", 
    "owenr_name": "M/s Raja Rao Rambaksh Singh Shiksha Prasar Samiti", 
    "unique_property_id": "234C340U333P1"
},
{
    "postal_add": "A-153/45, 2F, Block-A, Greenwood City, Gurugram", 
    "zone": "4", 
    "gender": "", 
    "area_name": "Greenwood City", 
    "relation_type": "W/O", 
    "relation_name": "Dr. Ajay Sharma", 
    "mobile_no": "9829114188", 
    "new_postal_add": "", 
    "owenr_name": "Mrs. Marina Sharma", 
    "unique_property_id": "234C340U333P2"
},
{
    "postal_add": "Plot No. 30-A, Block-H, Residency Green, Greenwood City, Sector-46, Gurugram", 
    "zone": "4", 
    "gender": "", 
    "area_name": "Greenwood City", 
    "relation_type": "", 
    "relation_name": "", 
    "mobile_no": "9811109142", 
    "new_postal_add": "", 
    "owenr_name": "Sh. Davinder Pal Singh & Smt. Paramjeet Kaur", 
    "unique_property_id": "234C806U192A"
},
{
    "postal_add": "M-829, Mayfield Garden, Sector-51, Gurugram", 
    "zone": "4", 
    "gender": "", 
    "area_name": "SECTOR 51", 
    "relation_type": "", 
    "relation_name": "", 
    "mobile_no": "9818192091", 
    "new_postal_add": "", 
    "owenr_name": "Mr. Deepak Yadav & Mrs. Anita Yadav", 
    "unique_property_id": "241C1190U6A"
},
{
    "postal_add": "M-830, Mayfield Garden, Sector-51, Gurugram", 
    "zone": "4", 
    "gender": "", 
    "area_name": "SECTOR 51", 
    "relation_type": "", 
    "relation_name": "", 
    "mobile_no": "9818192091", 
    "new_postal_add": "", 
    "owenr_name": "Mr. Pawan Kumar & Mrs. Kiran Yadav", 
    "unique_property_id": "241C1190U6B"
},
{
    "postal_add": "M-828, Mayfield Garden, Sector-51, Gurugram", 
    "zone": "4", 
    "gender": "", 
    "area_name": "SECTOR 51", 
    "relation_type": "", 
    "relation_name": "", 
    "mobile_no": "9899757505", 
    "new_postal_add": "", 
    "owenr_name": "Mr. Ravinder Yadav & Mrs. Sunita", 
    "unique_property_id": "241C1190U6C"
},
{
    "postal_add": "M-827, Mayfield Garden, Sector-51, Gurugram", 
    "zone": "4", 
    "gender": "", 
    "area_name": "SECTOR 51", 
    "relation_type": "", 
    "relation_name": "", 
    "mobile_no": "9899757505", 
    "new_postal_add": "", 
    "owenr_name": "Mr. hoshiyar Singh & Mrs. Ramesh Devi", 
    "unique_property_id": "241C1190U6D"
},
{
    "postal_add": "M-826, Mayfield Garden, Sector-51, Gurugram", 
    "zone": "4", 
    "gender": "", 
    "area_name": "SECTOR 51", 
    "relation_type": "", 
    "relation_name": "", 
    "mobile_no": "9818192091", 
    "new_postal_add": "", 
    "owenr_name": "Mr. Omprakash & Mr. Raghubir Singh", 
    "unique_property_id": "241C1190U6E"
},
{
    "postal_add": "H.No. 425, 1F, Sector-51, Gurugram", 
    "zone": "4", 
    "gender": "", 
    "area_name": "SECTOR 51", 
    "relation_type": "", 
    "relation_name": "", 
    "mobile_no": "7428856657", 
    "new_postal_add": "", 
    "owenr_name": "Mr. Saurabh Mahendra & Mrs. Nidhi Mahendra", 
    "unique_property_id": "241C899UMA425A"
},
{
    "postal_add": "J-93, Block-J, Mayfield Garden, Sector-51, Gurugram", 
    "zone": "4", 
    "gender": "", 
    "area_name": "Sector 51 Mayfield Garden", 
    "relation_type": "", 
    "relation_name": "", 
    "mobile_no": "9911965979", 
    "new_postal_add": "", 
    "owenr_name": "Mr. Bhuvnesh Anand & Mrs. Sonia Anand & Mrs. Geetanjali Chhauda", 
    "unique_property_id": "244C1139U58A"
},
{
    "postal_add": "26, 1F,  Block-D3, Spring Floors, Sector-50, Mayfield Garden, Gurugram", 
    "zone": "4", 
    "gender": "", 
    "area_name": "Sector 50 Mayfield Garden", 
    "relation_type": "W/O", 
    "relation_name": "Mr. Ram Gopal Sharma", 
    "mobile_no": "9811844230", 
    "new_postal_add": "", 
    "owenr_name": "Mrs. Sulochana Sharma", 
    "unique_property_id": "244C1420U507BA"
},
{
    "postal_add": "26, 2F, Block-D3, Spring Floors, Sector-50, Mayfield Garden, Gurugram", 
    "zone": "4", 
    "gender": "", 
    "area_name": "Sector 50 Mayfield Garden", 
    "relation_type": "S/O", 
    "relation_name": "S.S. Rao", 
    "mobile_no": "9811844230", 
    "new_postal_add": "", 
    "owenr_name": "Mr. Shekhar Rao", 
    "unique_property_id": "244C1420U507BA1"
},
{
    "postal_add": "C222, 2F, Sector 50, Mayfield Garden, Gurugram", 
    "zone": "4", 
    "gender": "", 
    "area_name": "Sector 50 Mayfield Garden", 
    "relation_type": "S/O", 
    "relation_name": "Sh. Lakhmi Chand Jain", 
    "mobile_no": "9810044221", 
    "new_postal_add": "", 
    "owenr_name": "Dinesh Kumar Jain", 
    "unique_property_id": "244C1492UC29P1572F"
},
{
    "postal_add": "C222, 2F, Sector 50, Mayfield Garden Gurugram", 
    "zone": "4", 
    "gender": "", 
    "area_name": "Sector 50 Mayfield Garden", 
    "relation_type": "S/O", 
    "relation_name": "Sh. Lakhmi Chand Jain", 
    "mobile_no": "9810044221", 
    "new_postal_add": "", 
    "owenr_name": "Dinesh Kumar Jain", 
    "unique_property_id": "244C1492UC29P157P2F"
},
{
    "postal_add": "C-135, 1F, Mayfield Garden, Sector-50, Gurugram", 
    "zone": "4", 
    "gender": "", 
    "area_name": "Sector 50 Mayfield Garden", 
    "relation_type": "", 
    "relation_name": "", 
    "mobile_no": "9650733228", 
    "new_postal_add": "", 
    "owenr_name": "Mr. Shashi Kant Rattanpal & Mrs. Arti Rattanpal", 
    "unique_property_id": "244C1580U358SP1"
},
{
    "postal_add": "Shop No. 16, SS Plaza, Sector 47, Mayfield Garden, Gurugram", 
    "zone": "4", 
    "gender": "", 
    "area_name": "Sector 47 Mayfield Garden", 
    "relation_type": "", 
    "relation_name": "", 
    "mobile_no": "9811033566", 
    "new_postal_add": "", 
    "owenr_name": "Rajesh Kumar Sharma", 
    "unique_property_id": "244C1851U1SP16AA"
},
{
    "postal_add": "Shop No. 17, SS Plaza, Sector 47, Mayfield Garden, Gurugram", 
    "zone": "4", 
    "gender": "", 
    "area_name": "Sector 47 Mayfield Garden", 
    "relation_type": "", 
    "relation_name": "", 
    "mobile_no": "9811033566", 
    "new_postal_add": "", 
    "owenr_name": "Smt. Shachi Sharma", 
    "unique_property_id": "244C1851U1SP17AA"
},
{
    "postal_add": "Shop No. 18, SS Plaza, Sector 47, Mayfield Garden, Gurugram", 
    "zone": "4", 
    "gender": "", 
    "area_name": "Sector 47 Mayfield Garden", 
    "relation_type": "", 
    "relation_name": "", 
    "mobile_no": "9811033566", 
    "new_postal_add": "", 
    "owenr_name": "Smt. Shachi Sharma", 
    "unique_property_id": "244C1851U1SP18AA"
},
{
    "postal_add": "Shop No. 19, SS Plaza, Sector 47, Mayfield Garden, Gurugram", 
    "zone": "4", 
    "gender": "", 
    "area_name": "Sector 47 Mayfield Garden", 
    "relation_type": "", 
    "relation_name": "", 
    "mobile_no": "9811033566", 
    "new_postal_add": "", 
    "owenr_name": "Smt. Shachi Sharma", 
    "unique_property_id": "244C1851U1SP19AA"
},
{
    "postal_add": "Shop No. 21, SS Plaza, Sector 47, Mayfield Garden, Gurugram", 
    "zone": "4", 
    "gender": "", 
    "area_name": "Sector 47 Mayfield Garden", 
    "relation_type": "", 
    "relation_name": "", 
    "mobile_no": "9811033566", 
    "new_postal_add": "", 
    "owenr_name": "Sh. Amit Sharma", 
    "unique_property_id": "244C1851U1SP21AA"
},
{
    "postal_add": "Shop No. 22, SS Plaza, Sector 47, Mayfield Garden, Gurugram", 
    "zone": "4", 
    "gender": "", 
    "area_name": "Sector 47 Mayfield Garden", 
    "relation_type": "", 
    "relation_name": "", 
    "mobile_no": "9811033566", 
    "new_postal_add": "", 
    "owenr_name": "Sh. Rajesh Kumar Sharma", 
    "unique_property_id": "244C1851U1SP22AA"
},
{
    "postal_add": "Shop No. 23A, SS Plaza, Sector-47, Mayfield Garden, Gurugram", 
    "zone": "4", 
    "gender": "", 
    "area_name": "Sector 47 Mayfield Garden", 
    "relation_type": "", 
    "relation_name": "", 
    "mobile_no": "9463702302", 
    "new_postal_add": "", 
    "owenr_name": "Karambir Singh Rai, Harbir Singh Rai and Sarabjit Kaur", 
    "unique_property_id": "244C1851U1SP23AA"
},
{
    "postal_add": "Shop No. 23B, SS Plaza, Sector 47, Mayfield Garden, Gurugram", 
    "zone": "4", 
    "gender": "", 
    "area_name": "Sector 47 Mayfield Garden", 
    "relation_type": "", 
    "relation_name": "", 
    "mobile_no": "9811033566", 
    "new_postal_add": "", 
    "owenr_name": "Sh. Ram Sewak Sharma and Smt. Kalpana Sharma", 
    "unique_property_id": "244C1851U1SP23AB"
},
{
    "postal_add": "Shop No. 20, SS Plaza, Sector 47, Mayfield Garden, Gurugram", 
    "zone": "4", 
    "gender": "", 
    "area_name": "Sector 47 Mayfield Garden", 
    "relation_type": "", 
    "relation_name": "", 
    "mobile_no": "9811033566", 
    "new_postal_add": "", 
    "owenr_name": "Bhavanjit Kaur Lonial and Shachi Sharma", 
    "unique_property_id": "244C1851US1P20AA"
},
{
    "postal_add": "M-68, G.F, Mayfield Garden, Sector-51, Gurugram", 
    "zone": "4", 
    "gender": "", 
    "area_name": "Sector 51 Mayfield Garden", 
    "relation_type": "", 
    "relation_name": "", 
    "mobile_no": "9902420099", 
    "new_postal_add": "", 
    "owenr_name": "Sh. Laxmi Narayan Aggarwal & Smt. Raj Bala Aggarwal", 
    "unique_property_id": "244C267U1305BA"
},
{
    "postal_add": "M-198, 1F, Mayfield Garden, Sector-51, Gurugram", 
    "zone": "4", 
    "gender": "", 
    "area_name": "Sector 51 Mayfield Garden", 
    "relation_type": "", 
    "relation_name": "", 
    "mobile_no": "9958798077", 
    "new_postal_add": "", 
    "owenr_name": "Subrata Roy", 
    "unique_property_id": "244C365UMAM199AB"
},
{
    "postal_add": "N-209, 2F, Block-N, Mayfield Garden, Sector-51, Gurugram", 
    "zone": "4", 
    "gender": "", 
    "area_name": "Sector 51 Mayfield Garden", 
    "relation_type": "", 
    "relation_name": "", 
    "mobile_no": "9871728862", 
    "new_postal_add": "", 
    "owenr_name": "Ms. Shruti Garg & Mr. Saurabh Goyal", 
    "unique_property_id": "244C683U214P2"
},
{
    "postal_add": "OD-108, 1F, Orange Drive Street, Malibu Town, Gurugram", 
    "zone": "4", 
    "gender": "", 
    "area_name": "Malibu Town", 
    "relation_type": "", 
    "relation_name": "", 
    "mobile_no": "9818965424", 
    "new_postal_add": "", 
    "owenr_name": "Mr. Sachin Grover & Mrs. Shradha Subramanian Grover & Mr. Kewal Kishore Grover & Mrs. Madhu Bala Grover", 
    "unique_property_id": "246C1147U209HP5P3"
},
{
    "postal_add": "PD-57, 3F, Pine Drive Street, Malibu Town, Gurugram", 
    "zone": "4", 
    "gender": "", 
    "area_name": "Malibu Town", 
    "relation_type": "", 
    "relation_name": "", 
    "mobile_no": "9811157289", 
    "new_postal_add": "", 
    "owenr_name": "Mrs. Veena Garg & Mrs. Vijay Garg", 
    "unique_property_id": "246C128U147FGA3"
},
{
    "postal_add": "201-E, 2F, Good earth City Center, Malibu Town, Gurugram", 
    "zone": "4", 
    "gender": "", 
    "area_name": "Malibu Town", 
    "relation_type": "W/O", 
    "relation_name": "Sh. Sudarshan Kumar Kohli", 
    "mobile_no": "9811513417", 
    "new_postal_add": "", 
    "owenr_name": "Smt. Kumkum Kohli", 
    "unique_property_id": "246C1351UP338P1"
},
{
    "postal_add": "201-C, 2F, Good Earth City Center, Malibu Town, Gurugram", 
    "zone": "4", 
    "gender": "", 
    "area_name": "Malibu Town", 
    "relation_type": "S/O", 
    "relation_name": "Mr. Kanya Ram Punia", 
    "mobile_no": "9717796766", 
    "new_postal_add": "", 
    "owenr_name": "Mr. Umed Singh Punia", 
    "unique_property_id": "246C1351UP338P2"
},
{
    "postal_add": "201-C, 2F, Good Earth City Center, Malibu Town, Gurugram", 
    "zone": "4", 
    "gender": "", 
    "area_name": "Malibu Town", 
    "relation_type": "S/O", 
    "relation_name": "Mr. Kanya Ram Punia", 
    "mobile_no": "9717796766", 
    "new_postal_add": "", 
    "owenr_name": "Mr. Umed Singh Punia", 
    "unique_property_id": "246C1351UP338P2"
},
{
    "postal_add": "201-D, 2F, Good Earth City Center, Malibu Town, Gurugram", 
    "zone": "4", 
    "gender": "", 
    "area_name": "Malibu Town", 
    "relation_type": "S/O", 
    "relation_name": "Mr. Ganga Bishan Choudhary", 
    "mobile_no": "9717796770", 
    "new_postal_add": "", 
    "owenr_name": "Mr. Rajendra Choudhary", 
    "unique_property_id": "246C1351UP338P3"
},
{
    "postal_add": "BS-04, 2F, Birch Street, Malibu Town, Gurugram", 
    "zone": "4", 
    "gender": "", 
    "area_name": "Malibu Town", 
    "relation_type": "W/O", 
    "relation_name": "Mr. Radhey Shyam", 
    "mobile_no": "9810294771", 
    "new_postal_add": "", 
    "owenr_name": "Mrs. Bimla Arya", 
    "unique_property_id": "246C255U93A"
},
{
    "postal_add": "G-121, Spaze Platinum Tower, Mailbu Town, Gurugram. ", 
    "zone": "4", 
    "gender": "", 
    "area_name": "Malibu Town", 
    "relation_type": "", 
    "relation_name": "", 
    "mobile_no": "9711387456", 
    "new_postal_add": "", 
    "owenr_name": "Sh. Vikas Aneja & Smt. Anu Aneja", 
    "unique_property_id": "246C2U1180P198P1"
},
{
    "postal_add": "502, 5F, Spaze Platinum Tower, Malibu Town, Gurugram", 
    "zone": "4", 
    "gender": "", 
    "area_name": "Malibu Town", 
    "relation_type": "S/O", 
    "relation_name": "Sh. K S Tanwar", 
    "mobile_no": "9810688266", 
    "new_postal_add": "", 
    "owenr_name": "Mr. Mehar Chand Tanwar", 
    "unique_property_id": "246C2U180P33A"
},
{
    "postal_add": "17, 1F, Drive Street, Malibu Town, Gurugram", 
    "zone": "4", 
    "gender": "", 
    "area_name": "Malibu Town", 
    "relation_type": "W/O", 
    "relation_name": "Sh. Subhash Chandra Paul", 
    "mobile_no": "9818805695", 
    "new_postal_add": "", 
    "owenr_name": "Mrs. Shipra Paul", 
    "unique_property_id": "246C325UMP17A"
},
{
    "postal_add": "55, 2F, Cedar Drive Street, Malibu Town, Gurugram", 
    "zone": "4", 
    "gender": "", 
    "area_name": "Malibu Town", 
    "relation_type": "", 
    "relation_name": "", 
    "mobile_no": "8383918282", 
    "new_postal_add": "", 
    "owenr_name": "Mr. Rakesh Malhotra & Mrs. Seema Malhotra", 
    "unique_property_id": "246C619U250B"
},
{
    "postal_add": "G-133, 1F, South City-2, Gurugram", 
    "zone": "4", 
    "gender": "", 
    "area_name": "South City 2", 
    "relation_type": "", 
    "relation_name": "", 
    "mobile_no": "8506060418", 
    "new_postal_add": "", 
    "owenr_name": "Mr. Omkar Rai & Mrs. Vandana Rai", 
    "unique_property_id": "247C1152U108P1"
},
{
    "postal_add": "G-133, 2F, South City-2, Gurugram", 
    "zone": "4", 
    "gender": "", 
    "area_name": "South City 2", 
    "relation_type": "", 
    "relation_name": "", 
    "mobile_no": "8506060418", 
    "new_postal_add": "", 
    "owenr_name": "Sh. Vivek Singh & Smt. Vandana Singh", 
    "unique_property_id": "247C1152U108P2"
},
{
    "postal_add": "G-130, 1F, South City-2, Gurugram", 
    "zone": "4", 
    "gender": "", 
    "area_name": "South City 2", 
    "relation_type": "", 
    "relation_name": "", 
    "mobile_no": "9582216855", 
    "new_postal_add": "", 
    "owenr_name": "Mr. Kapil Arora & Mrs. Anshul Arora", 
    "unique_property_id": "247C1155U106P1"
},
{
    "postal_add": "G-130, 2F, South City-2, Gurugram", 
    "zone": "4", 
    "gender": "", 
    "area_name": "South City 2", 
    "relation_type": "S/O", 
    "relation_name": "Sh. Balram Malik", 
    "mobile_no": "9413355541", 
    "new_postal_add": "", 
    "owenr_name": "Mr. Bhuvnish Malik", 
    "unique_property_id": "247C1155U106P2"
},
{
    "postal_add": "D-17, 2F, South City-2, Gurugram", 
    "zone": "4", 
    "gender": "", 
    "area_name": "South City 2", 
    "relation_type": "", 
    "relation_name": "", 
    "mobile_no": "9350548589", 
    "new_postal_add": "", 
    "owenr_name": "Mr. Ajay Singh Rathee & Aparna Rathee", 
    "unique_property_id": "247C1500U132A"
},
{
    "postal_add": "C-115, 1F, South City-2, Gurugram", 
    "zone": "4", 
    "gender": "", 
    "area_name": "South City 2", 
    "relation_type": "", 
    "relation_name": "", 
    "mobile_no": "9416050424", 
    "new_postal_add": "", 
    "owenr_name": "Mr. V. K Sangwan", 
    "unique_property_id": "247C1681U20P1"
},
{
    "postal_add": "C-115, 2F, South City-2, Gurugram", 
    "zone": "4", 
    "gender": "", 
    "area_name": "South City 2", 
    "relation_type": "", 
    "relation_name": "", 
    "mobile_no": "9818220025", 
    "new_postal_add": "", 
    "owenr_name": "Sh. G.L. Khurana", 
    "unique_property_id": "247C1681U20P2"
},
{
    "postal_add": "172, 1F, Unitech Arcadia, Block C, South City 2, Gurugram", 
    "zone": "4", 
    "gender": "", 
    "area_name": "South City 2", 
    "relation_type": "", 
    "relation_name": "", 
    "mobile_no": "9810355578", 
    "new_postal_add": "", 
    "owenr_name": "Mr. Kapil Kalra S/o Mr. Mahendra Prakash Kalra and Mr. Shubh Kalra S/o Mr. Vishal Kalra", 
    "unique_property_id": "247C696U244P570A"
},
{
    "postal_add": "15/4, 1F, Crimson Park West, Acacia-4, Vatika City, Sector-49, Gurugram", 
    "zone": "4", 
    "gender": "", 
    "area_name": "Sector 49", 
    "relation_type": "", 
    "relation_name": "", 
    "mobile_no": "9910941197", 
    "new_postal_add": "", 
    "owenr_name": "Mr. Jeetendra Rathore & Mrs. Swati Rathore & Mr. Balveer Rathore", 
    "unique_property_id": "248C166U15P4A"
},
{
    "postal_add": "OF-1018A, 10F, Tower B4, Spaze Itech Park, Sector 49, Gurugram", 
    "zone": "4", 
    "gender": "", 
    "area_name": "Sector 49", 
    "relation_type": "", 
    "relation_name": "", 
    "mobile_no": "8750041016", 
    "new_postal_add": "", 
    "owenr_name": "Mr. Anurag Mittal and Mrs. Monika Mittal", 
    "unique_property_id": "248C26UB4P1518A"
},
{
    "postal_add": "241, 2F, Universal Trade Tower, Sohna Road, Sector-49, Gurugram", 
    "zone": "4", 
    "gender": "", 
    "area_name": "SECTOR 49", 
    "relation_type": "D/O", 
    "relation_name": "Mr. Sunil Arora", 
    "mobile_no": "8178622550", 
    "new_postal_add": "", 
    "owenr_name": "Ms. Arshia Arora", 
    "unique_property_id": "248C99UUTP139AP1"
},
{
    "postal_add": "242, 2F, Universal Trade Tower, Sohna Road, Sector-49, Gurugram", 
    "zone": "4", 
    "gender": "", 
    "area_name": "SECTOR 49", 
    "relation_type": "", 
    "relation_name": "", 
    "mobile_no": "8178622550", 
    "new_postal_add": "", 
    "owenr_name": "Mr. Rohan Mahender Arora", 
    "unique_property_id": "248C99UUTP139AP2"
},
{
    "postal_add": "12, G.F. Universal Trade Tower, Sohna Road, Sector-49, Gurugram", 
    "zone": "4", 
    "gender": "", 
    "area_name": "SECTOR 49", 
    "relation_type": "", 
    "relation_name": "", 
    "mobile_no": "9811061071", 
    "new_postal_add": "", 
    "owenr_name": "Mr. Harinder Singh & Mrs. Charanjeet Kaur", 
    "unique_property_id": "248C99UUTP14P1"
},
{
    "postal_add": "P-82, 2F ,ASHIYAN SILVER OREST VILLAS, UPPAL SOUTHEND,GURUGRAM", 
    "zone": "4", 
    "gender": "", 
    "area_name": "Uppal Southend", 
    "relation_type": "", 
    "relation_name": "", 
    "mobile_no": "9350454132", 
    "new_postal_add": "", 
    "owenr_name": "", 
    "unique_property_id": "249C309U102P2"
},
{
    "postal_add": "247, 1F, BLOCK S, UPPAL SOUTHEND, GURUGRAM", 
    "zone": "4", 
    "gender": "", 
    "area_name": "Uppal Southend", 
    "relation_type": "", 
    "relation_name": "", 
    "mobile_no": "9899996411", 
    "new_postal_add": "", 
    "owenr_name": "PANKAJ NAGPAL", 
    "unique_property_id": "249C641U101A"
},
{
    "postal_add": "S-24, 1F, UPPAL SOUTHEND , GURUGRAM", 
    "zone": "4", 
    "gender": "", 
    "area_name": "Uppal Southend", 
    "relation_type": "", 
    "relation_name": "", 
    "mobile_no": "9829077335", 
    "new_postal_add": "", 
    "owenr_name": "satinder seth s/o satya pal seth and meena seth w/o satinder seth and poorti seth D/o satinder seth", 
    "unique_property_id": "249C727U247P1"
},
{
    "postal_add": "S-24, 2F, UPPAL SOUTHEND, GURUGRAM", 
    "zone": "4", 
    "gender": "", 
    "area_name": "Uppal Southend", 
    "relation_type": "", 
    "relation_name": "", 
    "mobile_no": "9829077335", 
    "new_postal_add": "", 
    "owenr_name": "SATINDER SETH S/O SATYA PAL SETH AND MEENA SETH W/O SATINDER SETH AND TRIPTEE TANEJA W/O SAMIR TANEJA", 
    "unique_property_id": "249C727U247P2"
},
{
    "postal_add": "S-24, 3F, UPPAL SOUTHEND ,GURUGRAM", 
    "zone": "4", 
    "gender": "", 
    "area_name": "Uppal Southend", 
    "relation_type": "", 
    "relation_name": "", 
    "mobile_no": "9829077335", 
    "new_postal_add": "", 
    "owenr_name": "", 
    "unique_property_id": "249C727U247P3"
},
{
    "postal_add": "S-23, 1F, BLOCK-S, UPPAL SOUTHEND, GURUGRAM", 
    "zone": "4", 
    "gender": "", 
    "area_name": "Uppal Southend", 
    "relation_type": "", 
    "relation_name": "", 
    "mobile_no": "8130361666", 
    "new_postal_add": "", 
    "owenr_name": "AJAY KUMAR MUDGIL S/O BAL KRISHAN MUDGIL AND ASTHA MUDGIL W/O AJAY KUMAR MUDGIL", 
    "unique_property_id": "249C728U246A"
},
{
    "postal_add": "S-23, 2F, BLOCK-S, UPPAL SOUTHEND,GURUGRAM", 
    "zone": "4", 
    "gender": "", 
    "area_name": "Uppal Southend", 
    "relation_type": "", 
    "relation_name": "", 
    "mobile_no": "8130361666", 
    "new_postal_add": "", 
    "owenr_name": "", 
    "unique_property_id": "249C728U246B"
},
{
    "postal_add": "W-32, 1F, UPPAL SOUTHEND,GURUGRAM", 
    "zone": "4", 
    "gender": "", 
    "area_name": "Uppal Southend", 
    "relation_type": "", 
    "relation_name": "", 
    "mobile_no": "9873392366", 
    "new_postal_add": "", 
    "owenr_name": "", 
    "unique_property_id": "249C785U57A"
},
{
    "postal_add": "W-32, 2F, UPPAL SOUTHEND, GURUGRAM", 
    "zone": "4", 
    "gender": "", 
    "area_name": "Uppal Southend", 
    "relation_type": "", 
    "relation_name": "", 
    "mobile_no": "9873392366", 
    "new_postal_add": "", 
    "owenr_name": "", 
    "unique_property_id": "249C785U57B"
},
{
    "postal_add": "B-117, 3F, ROSEWOOD CITY, GURUGRAM", 
    "zone": "4", 
    "gender": "", 
    "area_name": "Rosewood City", 
    "relation_type": "W/O", 
    "relation_name": "SURENDER KUMAR YADAV", 
    "mobile_no": "9811820900", 
    "new_postal_add": "", 
    "owenr_name": "SANGEETA YADAV", 
    "unique_property_id": "252C208U117A"
},
{
    "postal_add": "C-131, 1F, ROSEWOOD CITY, GURUGRAM", 
    "zone": "4", 
    "gender": "", 
    "area_name": "Rosewood City", 
    "relation_type": "", 
    "relation_name": "", 
    "mobile_no": "9811954444", 
    "new_postal_add": "", 
    "owenr_name": "RAJNEESH CHOPRA S/O I.R. CHOPRA AND GEETA CHOPRA W/O RAJNEESH CHOPRA", 
    "unique_property_id": "252C311UC131B"
},
{
    "postal_add": "132, 1F, DEERWOOD CHASE, NIRVANA, GURUGRAM", 
    "zone": "4", 
    "gender": "", 
    "area_name": "Nirvana", 
    "relation_type": "S/O", 
    "relation_name": "LATE S. GURBACHAN SINGH", 
    "mobile_no": "9711605011", 
    "new_postal_add": "", 
    "owenr_name": "PAWANJIT SINGH", 
    "unique_property_id": "253C197UMA132A"
},
{
    "postal_add": "132, 2F, DEERWOOD CHASE, NIRVANA, GURUGRAM", 
    "zone": "4", 
    "gender": "", 
    "area_name": "Nirvana", 
    "relation_type": "", 
    "relation_name": "", 
    "mobile_no": "9711605011", 
    "new_postal_add": "", 
    "owenr_name": "", 
    "unique_property_id": "253C197UMA132B"
},
{
    "postal_add": "119, 1F, DEERWOOD CHASE, NIRVANA, GURUGRAM", 
    "zone": "4", 
    "gender": "", 
    "area_name": "Nirvana", 
    "relation_type": "", 
    "relation_name": "", 
    "mobile_no": "9312640845", 
    "new_postal_add": "", 
    "owenr_name": "ROHIT", 
    "unique_property_id": "253C241UMA119A"
},
{
    "postal_add": "119 , 2F , DEERWOOD CHASE, NIRVANA, GURUGRAM", 
    "zone": "4", 
    "gender": "", 
    "area_name": "Nirvana", 
    "relation_type": "", 
    "relation_name": "", 
    "mobile_no": "9312640845", 
    "new_postal_add": "", 
    "owenr_name": "SANDEEP BAKHSHI", 
    "unique_property_id": "253C241UMA119B"
},
{
    "postal_add": "90B, 2F, SUSHANT LOK PHASE 3 EXTN, GURUGRAM", 
    "zone": "4", 
    "gender": "", 
    "area_name": "Sushant Lok Phase 3 Extn", 
    "relation_type": "", 
    "relation_name": "", 
    "mobile_no": "9818349447", 
    "new_postal_add": "", 
    "owenr_name": "YASHIN SHARMA", 
    "unique_property_id": "256C559UMA90BB"
},
{
    "postal_add": "E-149, 2F, SUSHANT RESIDENCY, SUSHANT LOK PHASE 3, GURUGRAM", 
    "zone": "4", 
    "gender": "", 
    "area_name": "Sushant Lok Phase 3 Extn", 
    "relation_type": "", 
    "relation_name": "", 
    "mobile_no": "9560333882", 
    "new_postal_add": "", 
    "owenr_name": "", 
    "unique_property_id": "256C723U73A2"
},
{
    "postal_add": "G-1232, SUSHANT LOK 2, GURUGRAM", 
    "zone": "4", 
    "gender": "", 
    "area_name": "SECTOR 57", 
    "relation_type": "W/O", 
    "relation_name": "SHRI HEMCHAND", 
    "mobile_no": "9810146757", 
    "new_postal_add": "", 
    "owenr_name": "BRIJESH", 
    "unique_property_id": "257C1076UA4P1"
},
{
    "postal_add": "1502, 1F, SECTOR-57, GURUGRAM", 
    "zone": "4", 
    "gender": "", 
    "area_name": "SECTOR 57", 
    "relation_type": "", 
    "relation_name": "", 
    "mobile_no": "9899292003", 
    "new_postal_add": "", 
    "owenr_name": "MANOJ AHLAWAT S/O JASBIR SINGH AND SANGEETA AHLAWAT W/O MANOJ AHLAWAT", 
    "unique_property_id": "257C557U1502A"
},
{
    "postal_add": "1502, 2F, SECTOR-57, GURUGRAM", 
    "zone": "4", 
    "gender": "", 
    "area_name": "SECTOR 57", 
    "relation_type": "", 
    "relation_name": "", 
    "mobile_no": "9873722954", 
    "new_postal_add": "", 
    "owenr_name": "", 
    "unique_property_id": "257C557U1502B"
},
{
    "postal_add": "C/124A, 1F, NEAR FLEXY HOME, SUSHANT LOK PHASE 3, GURUGRAM", 
    "zone": "4", 
    "gender": "", 
    "area_name": "Sushant Lok Phase 3", 
    "relation_type": "", 
    "relation_name": "", 
    "mobile_no": "9810266829", 
    "new_postal_add": "", 
    "owenr_name": "", 
    "unique_property_id": "260C131U346A"
},
{
    "postal_add": "C/124A, 2F, NEAR FLEXY HOME, SUSHANT LOK PHASE 3, GURUGRAM", 
    "zone": "4", 
    "gender": "", 
    "area_name": "Sushant Lok Phase 3", 
    "relation_type": "", 
    "relation_name": "", 
    "mobile_no": "9810266829", 
    "new_postal_add": "", 
    "owenr_name": "", 
    "unique_property_id": "260C131U346B"
},
{
    "postal_add": "A/203, 1F, SUSHANT LOK PHASE 3, GURUGRAM", 
    "zone": "4", 
    "gender": "", 
    "area_name": "Sushant Lok Phase 3", 
    "relation_type": "", 
    "relation_name": "", 
    "mobile_no": "9810112434", 
    "new_postal_add": "", 
    "owenr_name": "NISHANK S/O ANIL KUMAR SHARMA AND ANIL KUMAR SHARMA S/O SURESH CHAND SHARMA", 
    "unique_property_id": "260C2363U463A"
},
{
    "postal_add": "A/120, 1F, FLORENCE SUPER, SUSHANT LOK PHASE 3, GURUGRAM", 
    "zone": "4", 
    "gender": "", 
    "area_name": "Sushant Lok Phase 3", 
    "relation_type": "", 
    "relation_name": "", 
    "mobile_no": "9891120806", 
    "new_postal_add": "", 
    "owenr_name": "ANITA GUPTA W/O VED PARKASH GUPTA AND VED PARKASH GUPTA S/O ISHWAR CHAND GUPTA", 
    "unique_property_id": "260C2464U186A"
},
{
    "postal_add": "A/120, 2F, FLORENCE SUPER, SUSHANT LOK PHASE 3, GURUGRAM", 
    "zone": "4", 
    "gender": "", 
    "area_name": "Sushant Lok Phase 3", 
    "relation_type": "W/O", 
    "relation_name": "AEID RAZZAK KADHUM", 
    "mobile_no": "9891120806", 
    "new_postal_add": "", 
    "owenr_name": "ANITA KADHUM ", 
    "unique_property_id": "260C2464U186B"
},
{
    "postal_add": "B/103A, 1F, SUSHANT LOK PHASE 3, GURUGRAM", 
    "zone": "4", 
    "gender": "", 
    "area_name": "Sushant Lok Phase 3", 
    "relation_type": "", 
    "relation_name": "", 
    "mobile_no": "9958884572", 
    "new_postal_add": "", 
    "owenr_name": "", 
    "unique_property_id": "260C410U150P1"
},
{
    "postal_add": "B/103A,2F, SUSHANT LOK PHASE 3, GURUGRAM", 
    "zone": "4", 
    "gender": "", 
    "area_name": "Sushant Lok Phase 3", 
    "relation_type": "", 
    "relation_name": "", 
    "mobile_no": "9958884572", 
    "new_postal_add": "", 
    "owenr_name": "", 
    "unique_property_id": "260C410U150P2"
},
{
    "postal_add": "B/33, 3F, NEAR EDEN VILLA, SUSHANT LOK PHASE 3, GURUGRAM", 
    "zone": "4", 
    "gender": "", 
    "area_name": "Sushant Lok Phase 3", 
    "relation_type": "W/O", 
    "relation_name": "DAMAN KUMAR ABBEY", 
    "mobile_no": "8755184343", 
    "new_postal_add": "", 
    "owenr_name": "SHWETA ABBEY", 
    "unique_property_id": "260C432U237A"
},
{
    "postal_add": "B/47, 1F, SUSHANT LOK PHASE 3, GURUGRAM", 
    "zone": "4", 
    "gender": "", 
    "area_name": "Sushant Lok Phase 3", 
    "relation_type": "", 
    "relation_name": "", 
    "mobile_no": "9205602399", 
    "new_postal_add": "", 
    "owenr_name": "ANUJ THUKRAL S/O ASHOK KUMAR THUKRAL AND ASHOK KUMAR THUKRAL S/O LATE.SH HANSRAJ THUKRAL", 
    "unique_property_id": "260C446U192A"
},
{
    "postal_add": "F-250, 1F, ROYAL RESIDENCY, SUSHANT LOK PHASE 2, GURUGRAM", 
    "zone": "4", 
    "gender": "", 
    "area_name": "Sushant Lok Phase 2", 
    "relation_type": "S/O", 
    "relation_name": "DR. GAUTAM BISWAS", 
    "mobile_no": "9811696335", 
    "new_postal_add": "", 
    "owenr_name": "KRISHNENDU BISWAS", 
    "unique_property_id": "261C1851U147P1"
},
{
    "postal_add": "G-231, 1F, SUSHANT FLOORS, SUSHANT LOK PHASE 2, GURUGRAM", 
    "zone": "4", 
    "gender": "", 
    "area_name": "Sushant Lok Phase 2", 
    "relation_type": "", 
    "relation_name": "", 
    "mobile_no": "9717630112", 
    "new_postal_add": "", 
    "owenr_name": "ABHAY MISHRA S/O U.N. MISHRA AND NISHA MISHRA W/O ABHAY MISHRA", 
    "unique_property_id": "261C2324U189PA1"
},
{
    "postal_add": "G-231, 2F, SUSHANT FLOORS, SUSHANT LOK PHASE 2, GURUGRAM", 
    "zone": "4", 
    "gender": "", 
    "area_name": "Sushant Lok Phase 2", 
    "relation_type": "", 
    "relation_name": "", 
    "mobile_no": "9717630112", 
    "new_postal_add": "", 
    "owenr_name": "", 
    "unique_property_id": "261C2324U189PA2"
},
{
    "postal_add": "G-67, 1F, SUSHANT FLOORS, SUSHANT LOK PHASE 2, GURUGRAM", 
    "zone": "4", 
    "gender": "", 
    "area_name": "Sushant Lok Phase 2", 
    "relation_type": "", 
    "relation_name": "", 
    "mobile_no": "9650080487", 
    "new_postal_add": "", 
    "owenr_name": "BHAWNA SINGLA", 
    "unique_property_id": "261C2379U43A"
},
{
    "postal_add": "G-67, 2F, SUSHANT FLOORS, SUSHANT LOK PHASE 2, GURUGRAM", 
    "zone": "4", 
    "gender": "", 
    "area_name": "Sushant Lok Phase 2", 
    "relation_type": "", 
    "relation_name": "", 
    "mobile_no": "9650080487", 
    "new_postal_add": "", 
    "owenr_name": "BHAWNA SINGLA", 
    "unique_property_id": "261C2379U43B"
},
{
    "postal_add": "G-67, 4F, SUSHANT FLOORS, SUSHANT LOK PHASE 2, GURUGRAM", 
    "zone": "4", 
    "gender": "", 
    "area_name": "Sushant Lok Phase 2", 
    "relation_type": "", 
    "relation_name": "", 
    "mobile_no": "9650080487", 
    "new_postal_add": "", 
    "owenr_name": "BHAWNA SINGLA", 
    "unique_property_id": "261C2379U43D"
},
{
    "postal_add": "G-126A,1F,Sushant Floors, Sushant Lok Phase 2", 
    "zone": "4", 
    "gender": "", 
    "area_name": "Sushant Lok Phase 2", 
    "relation_type": "", 
    "relation_name": "", 
    "mobile_no": "9811767888", 
    "new_postal_add": "", 
    "owenr_name": "Sarita Aggarwal", 
    "unique_property_id": "261C2429U91P1"
},
{
    "postal_add": "G-126A, 2F, Sushant Floors, Sushant Lok Phase 2", 
    "zone": "4", 
    "gender": "", 
    "area_name": "Sushant Lok Phase 2", 
    "relation_type": "", 
    "relation_name": "", 
    "mobile_no": "9868366983", 
    "new_postal_add": "", 
    "owenr_name": "Kavita Sharma", 
    "unique_property_id": "261C2429U91P2"
},
{
    "postal_add": "G-225, 1F, SUSHANT FLOORS, SUSHANT LOK PHASE 2, GURUGRAM", 
    "zone": "4", 
    "gender": "", 
    "area_name": "Sushant Lok Phase 2", 
    "relation_type": "", 
    "relation_name": "", 
    "mobile_no": "9811109524", 
    "new_postal_add": "", 
    "owenr_name": "SANTOSH SINGHAL W/O DR. SATISH KUMAR SINGHAL AND DR. SANJEEV SINGHAL S/O DR. SATISH KUMAR SINGHAL", 
    "unique_property_id": "261C2563U206P3A"
},
{
    "postal_add": "G-225, 2F, SUSHANT FLOORS, SUSHANT LOK PHASE 2, GURUGRAM", 
    "zone": "4", 
    "gender": "", 
    "area_name": "Sushant Lok Phase 2", 
    "relation_type": "", 
    "relation_name": "", 
    "mobile_no": "9811109524", 
    "new_postal_add": "", 
    "owenr_name": "", 
    "unique_property_id": "261C2563U206P3B"
},
{
    "postal_add": "G-450, 1F, SUSHANT FLOORS, SUSHANT LOK PHASE 2, GURUGRAM", 
    "zone": "4", 
    "gender": "", 
    "area_name": "Sushant Lok Phase 2", 
    "relation_type": "", 
    "relation_name": "", 
    "mobile_no": "9891627899", 
    "new_postal_add": "", 
    "owenr_name": "DK BANSAL", 
    "unique_property_id": "261C2704U450P1"
},
{
    "postal_add": "G-450, 2F, SUSHANT FLOORS, SUSHANT LOK PHASE 2, GURUGRAM", 
    "zone": "4", 
    "gender": "", 
    "area_name": "Sushant Lok Phase 2", 
    "relation_type": "W/O", 
    "relation_name": "SARDARI LAL", 
    "mobile_no": "9891627899", 
    "new_postal_add": "", 
    "owenr_name": "CHANDER KANTA ", 
    "unique_property_id": "261C2704U450P2"
},
{
    "postal_add": "3028, 2F SECTOR 57, GURUGRAM", 
    "zone": "4", 
    "gender": "", 
    "area_name": "SECTOR 57", 
    "relation_type": "", 
    "relation_name": "", 
    "mobile_no": "9810791160", 
    "new_postal_add": "", 
    "owenr_name": "SUSHIL KUMAR SEHGAL", 
    "unique_property_id": "261C2838U3028P2"
},
{
    "postal_add": "3019, 2F, SECTOR 57, GURUGRAM", 
    "zone": "4", 
    "gender": "", 
    "area_name": "SECTOR 57", 
    "relation_type": "", 
    "relation_name": "", 
    "mobile_no": "9810084840", 
    "new_postal_add": "", 
    "owenr_name": "", 
    "unique_property_id": "261C2844U3019B"
},
{
    "postal_add": "3018, 1F, SECTOR 57, GURUGRAM", 
    "zone": "4", 
    "gender": "", 
    "area_name": "SECTOR 57", 
    "relation_type": "", 
    "relation_name": "", 
    "mobile_no": "9650166772", 
    "new_postal_add": "", 
    "owenr_name": "", 
    "unique_property_id": "261C2845U3018A"
},
{
    "postal_add": "3018, 2F, SECTOR 57, GURUGRAM", 
    "zone": "4", 
    "gender": "", 
    "area_name": "SECTOR 57", 
    "relation_type": "", 
    "relation_name": "", 
    "mobile_no": "9650166772", 
    "new_postal_add": "", 
    "owenr_name": "", 
    "unique_property_id": "261C2845U3018B"
},
{
    "postal_add": "3160,, 1F, SECTOR 57, GURUGRAM", 
    "zone": "4", 
    "gender": "", 
    "area_name": "SECTOR 57", 
    "relation_type": "", 
    "relation_name": "", 
    "mobile_no": "9041410273", 
    "new_postal_add": "", 
    "owenr_name": "MANINDER SINGH", 
    "unique_property_id": "261C3092U3160A"
},
{
    "postal_add": "3160, 2F, SECTOR 57, GURUGRAM", 
    "zone": "4", 
    "gender": "", 
    "area_name": "SECTOR 57", 
    "relation_type": "", 
    "relation_name": "", 
    "mobile_no": "9350100995", 
    "new_postal_add": "", 
    "owenr_name": "SUMANTA MANNA S/O LATE. SH. HARI SUDHAN MANNA AND ASIMA MANNA W/O SUMANATA MANNA", 
    "unique_property_id": "261C3092U3160B"
},
{
    "postal_add": "GUGA COLONY, BADSHAHPUR, GURUGRAM", 
    "zone": "4", 
    "gender": "", 
    "area_name": "Badshahpur", 
    "relation_type": "S/O", 
    "relation_name": "NARESH KUMAR VERMA", 
    "mobile_no": "9897704830", 
    "new_postal_add": "", 
    "owenr_name": "MANJEET VERMA ", 
    "unique_property_id": "319C147U188A"
},
{
    "postal_add": "NAI BASTI, BADSHAHPUR,GURUGRAM", 
    "zone": "4", 
    "gender": "", 
    "area_name": "Badshahpur", 
    "relation_type": "S/O", 
    "relation_name": "Dharam Singh", 
    "mobile_no": "9873219398", 
    "new_postal_add": "", 
    "owenr_name": "Parmod Kumar", 
    "unique_property_id": "319C3054U206B"
},
{
    "postal_add": "V.P.O.- Noopur Jharsa, Gurugram", 
    "zone": "4", 
    "gender": "", 
    "area_name": "Sector 68", 
    "relation_type": "S/O", 
    "relation_name": "Late Sh. Khushi Ram", 
    "mobile_no": "9873363607", 
    "new_postal_add": "", 
    "owenr_name": "Sh. Jai Narayan", 
    "unique_property_id": "320C124U54A"
},
{
    "postal_add": "V.P.O.- Noorpur Jharsa, Gurugram", 
    "zone": "4", 
    "gender": "", 
    "area_name": "Sector 68", 
    "relation_type": "S/O", 
    "relation_name": "Late Sh. Khushi Ram ", 
    "mobile_no": "9811437838", 
    "new_postal_add": "", 
    "owenr_name": "Sh. Nihal Singh", 
    "unique_property_id": "320C124U54B"
},
{
    "postal_add": "V.P.O.- Noorpur Jharsa, Gurugram", 
    "zone": "4", 
    "gender": "", 
    "area_name": "Sector 68", 
    "relation_type": "S/O", 
    "relation_name": "Late Sh. Khushi Ram", 
    "mobile_no": "8588813232", 
    "new_postal_add": "", 
    "owenr_name": "Sh. Bharat Singh", 
    "unique_property_id": "320C124U54C"
},
{
    "postal_add": "1108, 2F, Ansal Esencia, Sector-67, Gurugram", 
    "zone": "4", 
    "gender": "", 
    "area_name": "Sector 67", 
    "relation_type": "", 
    "relation_name": "", 
    "mobile_no": "9891236208", 
    "new_postal_add": "", 
    "owenr_name": "Mrs. Sudipta Mukherjee and Mr. Sumant Mukherjee", 
    "unique_property_id": "321C1084U60P1108A"
},
{
    "postal_add": "1108, 2F, Ansal Esencia, Sector-67, Gurugram", 
    "zone": "4", 
    "gender": "", 
    "area_name": "Sector 67", 
    "relation_type": "", 
    "relation_name": "", 
    "mobile_no": "9891236208", 
    "new_postal_add": "", 
    "owenr_name": "Mrs. Sudipta Mukherjee and Mr. Sumant Mukherjee", 
    "unique_property_id": "321C1084U60P1108A"
},
{
    "postal_add": "C-1208, 2F, Block-C, Esencia, Sector-67, Gurugram", 
    "zone": "4", 
    "gender": "", 
    "area_name": "Sector 67", 
    "relation_type": "W/O", 
    "relation_name": "Sh. Abhinav Kaushik", 
    "mobile_no": "9654910822", 
    "new_postal_add": "", 
    "owenr_name": "Mrs. Preetika Chadha Kaushik", 
    "unique_property_id": "321C1158U60P1208P2"
},
{
    "postal_add": "C-1208, 3F, Block-C, Esencia, Sector-67, Gurugram", 
    "zone": "4", 
    "gender": "", 
    "area_name": "Sector 67", 
    "relation_type": "", 
    "relation_name": "", 
    "mobile_no": "9654910822", 
    "new_postal_add": "", 
    "owenr_name": "Mr. Arun Shrivastava & Mrs. Rajni Rajesh Shrivastava", 
    "unique_property_id": "321C1158U60P1208P3"
},
{
    "postal_add": "C-1231, 1F, Block-C, Esencia, Sector-67, Gurugram", 
    "zone": "4", 
    "gender": "", 
    "area_name": "Sector 67", 
    "relation_type": "", 
    "relation_name": "", 
    "mobile_no": "7042500788", 
    "new_postal_add": "", 
    "owenr_name": "Mr. Rochak Khanna & Mrs. Payal Khanna & Mrs. Geeta Khanna", 
    "unique_property_id": "321C1175U60P1231P1"
},
{
    "postal_add": "C-1231, 2F, Block-C, Esencia, Sector-67, Gurugram", 
    "zone": "4", 
    "gender": "", 
    "area_name": "Sector 67", 
    "relation_type": "S/O", 
    "relation_name": "Mr. Suresh Pal Chaudhary", 
    "mobile_no": "9997188172", 
    "new_postal_add": "", 
    "owenr_name": "Mr. Sandeep Chaudhary", 
    "unique_property_id": "321C1175U60P1231P2"
},
{
    "postal_add": "Jail Road, Sector- 67, Gurugram", 
    "zone": "4", 
    "gender": "", 
    "area_name": "Sector 67", 
    "relation_type": "S/O", 
    "relation_name": "Shiv Singh", 
    "mobile_no": "9911161724", 
    "new_postal_add": "", 
    "owenr_name": "Umed Singh & Satish Kumar", 
    "unique_property_id": "321C797U54B"
},
{
    "postal_add": "4-C, GF, Universal Business Park, Sector-66, Gurugram", 
    "zone": "4", 
    "gender": "", 
    "area_name": "Sector 66", 
    "relation_type": "S/O", 
    "relation_name": "Sh. Vijay yerram", 
    "mobile_no": "9464541741", 
    "new_postal_add": "", 
    "owenr_name": "Puran Kumar Yerram", 
    "unique_property_id": "323C40U58P4"
}]
}
